<annotation>
	<folder>images</folder>
	<filename>Arm23.jpg</filename>
	<path>G:\My Drive\customTF2\images\Arm23.jpg</path>
	<source>
		<database>Unknown</database>
	</source>
	<size>
		<width>576</width>
		<height>1280</height>
		<depth>3</depth>
	</size>
	<segmented>0</segmented>
	<object>
		<name>Robot</name>
		<pose>Unspecified</pose>
		<truncated>0</truncated>
		<difficult>0</difficult>
		<bndbox>
			<xmin>18</xmin>
			<ymin>401</ymin>
			<xmax>518</xmax>
			<ymax>682</ymax>
		</bndbox>
	</object>
</annotation>
