<annotation>
	<folder>images</folder>
	<filename>Arm49.jpg</filename>
	<path>C:\Users\User\Desktop\Thesis\pose2\customTF2\images\Arm49.jpg</path>
	<source>
		<database>Unknown</database>
	</source>
	<size>
		<width>576</width>
		<height>1280</height>
		<depth>3</depth>
	</size>
	<segmented>0</segmented>
	<object>
		<name>Robot</name>
		<pose>Unspecified</pose>
		<truncated>1</truncated>
		<difficult>0</difficult>
		<bndbox>
			<xmin>1</xmin>
			<ymin>300</ymin>
			<xmax>564</xmax>
			<ymax>1059</ymax>
		</bndbox>
	</object>
</annotation>
